[
  {
    "id": "prod_001",
    "name": "Floral Summer Maxi Dress",
    "price": 59.99,
    "image_url": "https://picsum.photos/seed/dress1/200/200",
    "product_url": "https://yourd2csite.com/products/floral-maxi-dress-001",
    "category": "dresses",
    "gender": "female",
    "occasion_tags": ["casual", "summer", "beach", "daywear", "garden party"],
    "style_tags": ["boho", "relaxed", "flowy"],
    "color": "multi-color",
    "short_description": "A beautiful and airy floral maxi dress, perfect for casual summer days, beach outings, or garden parties. Its flowy design ensures comfort and a relaxed, bohemian style.",
    "master_category": "top & foot combined",
    "subcategory": "dress",
    "season": "summer",
    "sleeve_length": "sleeveless",
    "item_length": "maxi"
  },
  {
    "id": "prod_002",
    "name": "Men's Classic Polo Shirt",
    "price": 35.0,
    "image_url": "https://picsum.photos/seed/polo1/200/200",
    "product_url": "https://yourd2csite.com/products/polo-shirt-002",
    "category": "tops",
    "gender": "male",
    "occasion_tags": ["casual", "sports", "daily wear"],
    "style_tags": ["classic", "preppy"],
    "color": "navy blue",
    "short_description": "A timeless classic polo shirt for men, ideal for casual wear, sports, or everyday comfort. Features breathable fabric and a preppy, versatile style.",
    "master_category": "top",
    "subcategory": "polo shirt",
    "season": "all-season",
    "sleeve_length": "half sleeve",
    "item_length": "N/A"
  },
  {
    "id": "prod_003",
    "name": "Elegant Sequin Evening Gown",
    "price": 189.99,
    "image_url": "https://picsum.photos/seed/gown1/200/200",
    "product_url": "https://yourd2csite.com/products/sequin-evening-gown-003",
    "category": "dresses",
    "gender": "female",
    "occasion_tags": ["formal", "gala", "party", "evening"],
    "style_tags": ["glamorous", "elegant", "luxurious"],
    "color": "gold",
    "short_description": "Sparkling and glamorous evening gown, perfect for formal events, galas, and special parties. This luxurious sequin dress offers a truly elegant look.",
    "master_category": "top & foot combined",
    "subcategory": "gown",
    "season": "all-season",
    "sleeve_length": "sleeveless",
    "item_length": "full length" 
  },
  {
    "id": "prod_004",
    "name": "Unisex Running Shorts",
    "price": 29.99,
    "image_url": "https://picsum.photos/seed/shorts1/200/200",
    "product_url": "https://yourd2csite.com/products/running-shorts-004",
    "category": "bottoms",
    "gender": "unisex",
    "occasion_tags": ["sports", "workout", "casual"],
    "style_tags": ["athletic", "minimalist"],
    "color": "black",
    "short_description": "Lightweight and comfortable unisex running shorts, ideal for sports, workouts, or casual everyday wear. Features an athletic and minimalist design.",
    "master_category": "bottom",
    "subcategory": "shorts",
    "season": "summer",
    "sleeve_length": "N/A",
    "item_length": "short"
  },
  {
    "id": "prod_005",
    "name": "Cozy Knitted Sweater",
    "price": 79.5,
    "image_url": "https://picsum.photos/seed/sweater1/200/200",
    "product_url": "https://yourd2csite.com/products/knitted-sweater-005",
    "category": "sweaters",
    "gender": "male",
    "occasion_tags": ["casual", "winter", "cozy"],
    "style_tags": ["comfortable", "classic"],
    "color": "grey",
    "short_description": "A soft and cozy knitted sweater for men, perfect for casual winter days or just lounging. Offers comfortable and classic style.",
    "master_category": "top",
    "subcategory": "sweater",
    "season": "winter",
    "sleeve_length": "full sleeve",
    "item_length": "N/A"
  },
  {
    "id": "prod_006",
    "name": "Denim Jeans - Slim Fit",
    "price": 65.0,
    "image_url": "https://picsum.photos/seed/jeans1/200/200",
    "product_url": "https://yourd2csite.com/products/denim-jeans-006",
    "category": "bottoms",
    "gender": "unisex",
    "occasion_tags": ["casual", "daily wear"],
    "style_tags": ["classic", "versatile"],
    "color": "blue",
    "short_description": "Classic slim fit denim jeans suitable for everyday wear. A versatile and essential piece for any casual wardrobe.",
    "master_category": "bottom",
    "subcategory": "jeans",
    "season": "all-season",
    "sleeve_length": "N/A",
    "item_length": "full length"
  },
  {
    "id": "prod_007",
    "name": "Vibrant Tropical Hawaiian Shirt",
    "price": 45.0,
    "image_url": "https://picsum.photos/seed/hawaiianshirt1/200/200",
    "product_url": "https://yourd2csite.com/products/tropical-hawaiian-shirt-007",
    "category": "tops",
    "gender": "male",
    "occasion_tags": ["casual", "summer", "beach", "party", "vacation"],
    "style_tags": ["vibrant", "tropical", "relaxed", "fun"],
    "color": "multi-color",
    "short_description": "A vibrant and colorful tropical Hawaiian shirt, perfect for summer beach parties, vacations, or any casual fun occasion. Features a relaxed fit and eye-catching print.",
    "master_category": "top",
    "subcategory": "shirt",
    "season": "summer",
    "sleeve_length": "half sleeve",
    "item_length": "N/A"
  },
  {
    "id": "prod_008",
    "name": "Sleek Black Club Top",
    "price": 55.0,
    "image_url": "https://picsum.photos/seed/clubtop1/200/200",
    "product_url": "https://yourd2csite.com/products/black-club-top-008",
    "category": "tops",
    "gender": "female",
    "occasion_tags": ["party", "night out", "clubwear"],
    "style_tags": ["chic", "modern", "edgy", "sleek"],
    "color": "black",
    "short_description": "A sleek and stylish black top designed for a night out or clubbing. This modern piece offers a chic and edgy look for parties.",
    "master_category": "top",
    "subcategory": "top",
    "season": "all-season",
    "sleeve_length": "sleeveless",
    "item_length": "N/A"
  }
]